gidgetlab_kit/__init__.py
gidgetlab_kit/api.py
gidgetlab_kit/clone.py
gidgetlab_kit/command.py
gidgetlab_kit/commits.py
gidgetlab_kit/exceptions.py
gidgetlab_kit/get.py
gidgetlab_kit/models.py
gidgetlab_kit/pipelines.py
gidgetlab_kit/producers.py
gidgetlab_kit/tasks.py
gidgetlab_kit/util.py
gidgetlab_kit-0.7.2.dist-info/METADATA
gidgetlab_kit-0.7.2.dist-info/WHEEL
gidgetlab_kit-0.7.2.dist-info/entry_points.txt
gidgetlab_kit-0.7.2.dist-info/licenses/LICENSE
gidgetlab_kit-0.7.2.dist-info/RECORD
