Metadata-Version: 2.3
Name: gidgetlab-kit
Version: 0.7.2
Summary: Python package to interact with GitLab
Project-URL: Source, https://gitlab.com/beenje/gidgetlab-kit
Author-email: Benjamin Bertrand <beenje@gmail.com>
License-Expression: MIT
License-File: LICENSE
Keywords: async,gitlab
Requires-Python: >=3.9
Requires-Dist: gidgetlab
Requires-Dist: httpx
Requires-Dist: pydantic
Requires-Dist: python-dateutil
Requires-Dist: typer>=0.9.0
Provides-Extra: tests
Requires-Dist: pytest; extra == 'tests'
Requires-Dist: pytest-asyncio; extra == 'tests'
Requires-Dist: pytest-cov; extra == 'tests'
Requires-Dist: pytest-mock; extra == 'tests'
